daniel_lightrag_mcp/__init__.py
daniel_lightrag_mcp/__main__.py
daniel_lightrag_mcp/cli.py
daniel_lightrag_mcp/client.py
daniel_lightrag_mcp/mock_client.py
daniel_lightrag_mcp/models.py
daniel_lightrag_mcp/server.py
iflow_mcp_desimpkins_daniel_lightrag_mcp-0.1.0.dist-info/licenses/LICENSE
iflow_mcp_desimpkins_daniel_lightrag_mcp-0.1.0.dist-info/METADATA
iflow_mcp_desimpkins_daniel_lightrag_mcp-0.1.0.dist-info/WHEEL
iflow_mcp_desimpkins_daniel_lightrag_mcp-0.1.0.dist-info/entry_points.txt
iflow_mcp_desimpkins_daniel_lightrag_mcp-0.1.0.dist-info/top_level.txt
iflow_mcp_desimpkins_daniel_lightrag_mcp-0.1.0.dist-info/RECORD
